t2d/__init__.py
t2d/bot.py
t2d/decorators.py
t2d/utils.py
t2d-0.1.5.dist-info/LICENSE
t2d-0.1.5.dist-info/WHEEL
t2d-0.1.5.dist-info/METADATA
t2d-0.1.5.dist-info/RECORD
