Metadata-Version: 2.1
Name: t2d
Version: 0.1.5
Summary: Seamless integration between Typer and Discord.py for CLI Discord bots
Home-page: https://github.com/gabriel-milan/t2d
License: GPL-3.0-only
Keywords: discord,typer,cli,bot
Author: Gabriel Gazola Milan
Author-email: gabriel.gazola@poli.ufrj.br
Requires-Python: >=3.7,<4.0
Classifier: Development Status :: 3 - Alpha
Classifier: License :: OSI Approved :: GNU General Public License v3 (GPLv3)
Classifier: Programming Language :: Python :: 3
Classifier: Programming Language :: Python :: 3.10
Classifier: Programming Language :: Python :: 3.7
Classifier: Programming Language :: Python :: 3.8
Classifier: Programming Language :: Python :: 3.9
Requires-Dist: discord.py (>=1.7.3,<2.0.0)
Requires-Dist: importlib-metadata (>=1.0,<2.0); python_version < "3.8"
Requires-Dist: loguru (>=0.5.3,<0.6.0)
Requires-Dist: typer (>=0.4.0,<0.5.0)
Project-URL: Repository, https://github.com/gabriel-milan/t2d
